easy_eval/__init__.py
easy_eval/config.py
easy_eval/harness/__init__.py
easy_eval/harness/model.py
easy_eval/harness/tasks.py
easy_evaluator-0.1.0.dist-info/METADATA
easy_evaluator-0.1.0.dist-info/WHEEL
easy_evaluator-0.1.0.dist-info/top_level.txt
easy_evaluator-0.1.0.dist-info/RECORD
