Metadata-Version: 2.1
Name: easy-evaluator
Version: 0.1.0
Summary: A library for easy evaluation of language models
Home-page: https://github.com/Anindyadeep/easy_eval
Author: Anindyadeep
Author-email: proanindyadeep@gmail.com
License: UNKNOWN
Platform: UNKNOWN
Requires-Dist: fastapi ==0.108.0
Requires-Dist: lm-eval ==0.4.1
